LICENSE
MANIFEST.in
README.md
setup.cfg
setup.py
src/os_rotatefile/VERSION
src/os_rotatefile/__init__.py
src/os_rotatefile/rotatefile.py
src/os_rotatefile.egg-info/PKG-INFO
src/os_rotatefile.egg-info/SOURCES.txt
src/os_rotatefile.egg-info/dependency_links.txt
src/os_rotatefile.egg-info/not-zip-safe
src/os_rotatefile.egg-info/top_level.txt
tests/__init__.py
tests/test_rotatefile.py