Metadata-Version: 1.1
Name: os-rotatefile
Version: 0.2.0
Summary: Reading and writing size rotate file.
Home-page: https://github.com/cfhamlet/os-rotatefile
Author: Ozzy
Author-email: cfhamlet@gmail.com
License: MIT License
Platform: UNKNOWN
Classifier: Development Status :: 2 - Pre-Alpha
Classifier: Intended Audience :: Developers
Classifier: License :: OSI Approved :: MIT License
Classifier: Natural Language :: English
Classifier: Programming Language :: Python :: 2
Classifier: Programming Language :: Python :: 2.7
Classifier: Programming Language :: Python :: 3
Classifier: Programming Language :: Python :: 3.6
Classifier: Programming Language :: Python :: Implementation :: CPython
